{
  "course_name": "Computer Graphics",
  "description": "A survey of topics in computer graphics with an emphasis on fundamental techniques. Topics include: graphics hardware, fundamentals of three-dimensional graphics including modeling, projection, coordinate transformation, synthetic camera specification, color, lighting, shading, hidden surface removal, animation, and texture-mapping. We also cover the mathematical representation and programming specification of lines, planes, curves, and surfaces. Students will build graphics applications using a browser-based platform.",
  "details": "CRN: 28227; Credit Hours: 1; Current Enrollment: 25; Seats Available: 3; Max Enrollment: 28;",
  "distributions": "Distributions: MM - Mathematical Modeling and Problem Solving",
  "extra_info": [
    ""
  ],
  "id": "cs307",
  "linked_courses": "",
  "meeting_info": "Meeting Time(s): TF - 8:30 AM - 9:45 AM Loc: Science Center L Wing 180 Computer Science Computer Lab",
  "notes": "Notes:",
  "prereqs": "Prerequisites(s): CS 230 or permission of the instructor.",
  "professors": [
    [
      "Ellen Hildreth",
      "https://courses.wellesley.edu/faculty_profiles.php?user=ehildret"
    ]
  ],
  "section": "01",
  "semester": "202202",
  "term": null
}